[
    {
        "pointer": 0,
        "name": "GA",
        "size": 4
    },
    {
        "pointer": 1,
        "name": "GB",
        "size": 4
    },
    {
        "pointer": 2,
        "name": "GC",
        "size": 4
    },
    {
        "pointer": 3,
        "name": "GD",
        "size": 4
    },
    {
        "pointer": 128,
        "name": "IP",
        "size": 2
    },
    {
        "pointer": 129,
        "name": "SP",
        "size": 2,
        "data": "11110000 00000000"
    },
    {
        "pointer": 192,
        "name": "FL",
        "size": 1
    }
]
