[
    {
        "pointer": 0,
        "name": "GA",
        "size": 4,
        "children": {
            "AL": 0
        },
        "op_add": 0
    },
    {
        "pointer": 64,
        "name": "AL",
        "size": 1,
        "op_add": 0
    },
    {
        "pointer": 1,
        "name": "GB",
        "size": 4,
        "children": {
            "BL": 0
        },
        "op_add": 1
    },
    {
        "pointer": 65,
        "name": "BL",
        "size": 1,
        "op_add": 1
    },
    {
        "pointer": 2,
        "name": "GC",
        "size": 4,
        "children": {
            "CL": 0
        },
        "op_add": 2
    },
    {
        "pointer": 66,
        "name": "CL",
        "size": 1,
        "op_add": 2
    },
    {
        "pointer": 3,
        "name": "GD",
        "size": 4,
        "children": {
            "DL": 0
        },
        "op_add": 3
    },
    {
        "pointer": 67,
        "name": "DL",
        "size": 1,
        "op_add": 3
    },
    {
        "pointer": 128,
        "name": "IP",
        "size": 2
    },
    {
        "pointer": 129,
        "name": "SP",
        "size": 2,
        "data": "11110000 00000000"
    },
    {
        "pointer": 130,
        "name": "RI",
        "size": 2
    },
    {
        "pointer": 131,
        "name": "RS",
        "size": 2
    },
    {
        "pointer": 192,
        "name": "FL",
        "size": 1
    }
]
